looptimer/__init__.py
looptimer/looptimer.py
looptimer-1.1.0.dist-info/LICENSE
looptimer-1.1.0.dist-info/METADATA
looptimer-1.1.0.dist-info/WHEEL
looptimer-1.1.0.dist-info/top_level.txt
looptimer-1.1.0.dist-info/RECORD
