Metadata-Version: 2.1
Name: looptimer
Version: 1.1.0
Author-email: Bryan Johnson <d.bryan.johnson@gmail.com>
License: The MIT License (MIT)
Project-URL: Homepage, https://github.com/dbjohnson/looptimer
Keywords: timer,timing,progress
Classifier: License :: OSI Approved :: MIT License
Classifier: Programming Language :: Python
Classifier: Programming Language :: Python :: 3
Requires-Python: >=2.7
License-File: LICENSE
Provides-Extra: dev
Requires-Dist: bumpver ; extra == 'dev'
Requires-Dist: pytest ; extra == 'dev'
Requires-Dist: build ; extra == 'dev'
Requires-Dist: twine ; extra == 'dev'
